{
    "title": "Cisco Identity Intelligence - Failed Checks",
    "description": "This dashboard provides information about the Failed Checks generated on Cisco Identity Intelligence(OORT).",
    "widgets": [
        {
            "id": 5527090904543100,
            "definition": {
                "title": "",
                "banner_img": "https://www.gartner.com/imagesrv/apps/peerinsights/images/vendors/logos/cisco_wired-wireless-lan-access-infrastructure.png",
                "show_title": true,
                "type": "group",
                "layout_type": "ordered",
                "widgets": [
                    {
                        "id": 911775482073612,
                        "definition": {
                            "type": "note",
                            "content": "Gain better visibility into your organization's security events by monitoring Cisco Identity Intelligence (OORT) Failed Check logs with this dashboard. \n\nCisco Identity Intelligence, formerly known as Oort, is an identity provider application that offers advanced security features for managing user identities and access across an organization's network. It enables organizations to authenticate, authorize, and monitor user access to applications and resources efficiently. Cisco Identity Intelligence (Oort) helps organizations strengthen their security posture by providing robust identity and access management functionalities to protect against unauthorized access and security threats.\n\nFor Further reading, see:\n\n- [Cisco Identity Intelligence (OORT) - Documentation](https://docs.datadoghq.com/integrations/cisco_identity_intelligence)\n\n**Tips**\n- Use the timeframe selector in the top right of the dashboard to change the default timeframe.\n- Clone this dashboard to rearrange, modify and add widgets and visualizations.",
                            "background_color": "white",
                            "font_size": "14",
                            "text_align": "left",
                            "vertical_align": "top",
                            "show_tick": false,
                            "tick_pos": "50%",
                            "tick_edge": "left",
                            "has_padding": true
                        },
                        "layout": {
                            "x": 0,
                            "y": 0,
                            "width": 6,
                            "height": 5
                        }
                    }
                ]
            },
            "layout": {
                "x": 0,
                "y": 0,
                "width": 6,
                "height": 8
            }
        },
        {
            "id": 8694280567870332,
            "definition": {
                "title": "Cisco Identity Intelligence Logs Overview",
                "background_color": "vivid_blue",
                "show_title": true,
                "type": "group",
                "layout_type": "ordered",
                "widgets": [
                    {
                        "id": 7599790963799516,
                        "definition": {
                            "title": "Severity Over Time",
                            "title_size": "16",
                            "title_align": "left",
                            "show_legend": true,
                            "legend_layout": "horizontal",
                            "legend_columns": [
                                "avg",
                                "min",
                                "max",
                                "value",
                                "sum"
                            ],
                            "type": "timeseries",
                            "requests": [
                                {
                                    "formulas": [
                                        {
                                            "formula": "query1"
                                        }
                                    ],
                                    "queries": [
                                        {
                                            "data_source": "logs",
                                            "name": "query1",
                                            "indexes": [
                                                "*"
                                            ],
                                            "compute": {
                                                "aggregation": "count"
                                            },
                                            "group_by": [
                                                {
                                                    "facet": "@detail.severity",
                                                    "limit": 10,
                                                    "sort": {
                                                        "order": "desc",
                                                        "aggregation": "count"
                                                    }
                                                }
                                            ],
                                            "search": {
                                                "query": "source:cisco-identity-intelligence $Status $Detail-Type $Title $Check-Id $Region"
                                            },
                                            "storage": "hot"
                                        }
                                    ],
                                    "response_format": "timeseries",
                                    "style": {
                                        "palette": "dog_classic",
                                        "order_by": "values",
                                        "color_order": "shuffled",
                                        "line_type": "solid",
                                        "line_width": "normal"
                                    },
                                    "display_type": "line"
                                }
                            ]
                        },
                        "layout": {
                            "x": 0,
                            "y": 0,
                            "width": 6,
                            "height": 3
                        }
                    },
                    {
                        "id": 6665129572849076,
                        "definition": {
                            "title": "Total Failed Checks",
                            "title_size": "16",
                            "title_align": "left",
                            "type": "query_value",
                            "requests": [
                                {
                                    "response_format": "scalar",
                                    "queries": [
                                        {
                                            "data_source": "logs",
                                            "name": "query1",
                                            "indexes": [
                                                "*"
                                            ],
                                            "compute": {
                                                "aggregation": "count"
                                            },
                                            "group_by": [],
                                            "search": {
                                                "query": "source:cisco-identity-intelligence $Status $Detail-Type $Title $Check-Id $Region"
                                            },
                                            "storage": "hot"
                                        }
                                    ],
                                    "formulas": [
                                        {
                                            "formula": "query1"
                                        }
                                    ],
                                    "conditional_formats": [
                                        {
                                            "comparator": ">",
                                            "value": 0,
                                            "palette": "black_on_light_red"
                                        }
                                    ]
                                }
                            ],
                            "autoscale": true,
                            "precision": 2
                        },
                        "layout": {
                            "x": 0,
                            "y": 3,
                            "width": 3,
                            "height": 4
                        }
                    },
                    {
                        "id": 1082053023022250,
                        "definition": {
                            "title": "Top 10 IP With Failed Checks",
                            "title_size": "16",
                            "title_align": "left",
                            "type": "toplist",
                            "requests": [
                                {
                                    "queries": [
                                        {
                                            "data_source": "logs",
                                            "name": "query1",
                                            "indexes": [
                                                "*"
                                            ],
                                            "compute": {
                                                "aggregation": "cardinality",
                                                "metric": "@id"
                                            },
                                            "group_by": [
                                                {
                                                    "facet": "@network.ip.attributes.ip",
                                                    "limit": 10,
                                                    "sort": {
                                                        "order": "desc",
                                                        "aggregation": "cardinality",
                                                        "metric": "@id"
                                                    }
                                                }
                                            ],
                                            "search": {
                                                "query": "source:cisco-identity-intelligence $Status $Detail-Type $Title $Check-Id $Region"
                                            },
                                            "storage": "hot"
                                        }
                                    ],
                                    "response_format": "scalar",
                                    "formulas": [
                                        {
                                            "formula": "query1"
                                        }
                                    ],
                                    "sort": {
                                        "count": 10,
                                        "order_by": [
                                            {
                                                "type": "formula",
                                                "index": 0,
                                                "order": "desc"
                                            }
                                        ]
                                    }
                                }
                            ],
                            "style": {
                                "display": {
                                    "type": "stacked",
                                    "legend": "automatic"
                                }
                            }
                        },
                        "layout": {
                            "x": 3,
                            "y": 3,
                            "width": 3,
                            "height": 4
                        }
                    }
                ]
            },
            "layout": {
                "x": 6,
                "y": 0,
                "width": 6,
                "height": 8
            }
        },
        {
            "id": 1293337257504016,
            "definition": {
                "title": "Datadog Cloud SIEM",
                "title_align": "center",
                "background_color": "vivid_blue",
                "show_title": true,
                "type": "group",
                "layout_type": "ordered",
                "widgets": [
                    {
                        "id": 5996232744860254,
                        "definition": {
                            "type": "note",
                            "content": "Datadog Cloud SIEM analyzes and correlates Failed Checks logs to detect threats to your environment in real time. If you don't see signals please make sure you've enabled [Datadog Cloud SIEM](https://app.datadoghq.com/security?query=source%3Acisco-identity-intelligence%20&agg_m=count&agg_m_source=base&agg_t=count&column=time&fromUser=false&order=desc&start=1722941024113&end=1723027424113&paused=false). ",
                            "background_color": "blue",
                            "font_size": "14",
                            "text_align": "left",
                            "vertical_align": "center",
                            "show_tick": false,
                            "tick_pos": "50%",
                            "tick_edge": "left",
                            "has_padding": true
                        },
                        "layout": {
                            "x": 0,
                            "y": 0,
                            "width": 12,
                            "height": 1
                        }
                    },
                    {
                        "id": 5342373837676104,
                        "definition": {
                            "title": "CRITICALs",
                            "title_size": "16",
                            "title_align": "left",
                            "type": "query_value",
                            "requests": [
                                {
                                    "formulas": [
                                        {
                                            "formula": "query1"
                                        }
                                    ],
                                    "queries": [
                                        {
                                            "data_source": "security_signals",
                                            "name": "query1",
                                            "indexes": [
                                                "*"
                                            ],
                                            "compute": {
                                                "aggregation": "count"
                                            },
                                            "group_by": [],
                                            "search": {
                                                "query": "status:critical source:cisco-identity-intelligence $Status $Detail-Type $Title $Check-Id $Region"
                                            }
                                        }
                                    ],
                                    "response_format": "scalar",
                                    "conditional_formats": [
                                        {
                                            "comparator": ">",
                                            "value": 0,
                                            "palette": "custom_bg",
                                            "custom_bg_color": "#bc303c"
                                        }
                                    ]
                                }
                            ],
                            "autoscale": true,
                            "precision": 2
                        },
                        "layout": {
                            "x": 0,
                            "y": 1,
                            "width": 2,
                            "height": 2
                        }
                    },
                    {
                        "id": 3185915280408570,
                        "definition": {
                            "title": "MEDIUMs",
                            "title_size": "16",
                            "title_align": "left",
                            "type": "query_value",
                            "requests": [
                                {
                                    "response_format": "scalar",
                                    "queries": [
                                        {
                                            "data_source": "security_signals",
                                            "name": "query1",
                                            "indexes": [
                                                "*"
                                            ],
                                            "compute": {
                                                "aggregation": "count"
                                            },
                                            "group_by": [],
                                            "search": {
                                                "query": "status:medium source:cisco-identity-intelligence $Status $Detail-Type $Title $Check-Id $Region"
                                            }
                                        }
                                    ],
                                    "formulas": [
                                        {
                                            "formula": "query1"
                                        }
                                    ],
                                    "conditional_formats": [
                                        {
                                            "comparator": ">",
                                            "value": 0,
                                            "palette": "custom_bg",
                                            "custom_bg_color": "#e5a21c"
                                        }
                                    ]
                                }
                            ],
                            "autoscale": true,
                            "precision": 2
                        },
                        "layout": {
                            "x": 2,
                            "y": 1,
                            "width": 2,
                            "height": 2
                        }
                    },
                    {
                        "id": 2730357203389226,
                        "definition": {
                            "title": "Critical Security Signals",
                            "title_size": "16",
                            "title_align": "left",
                            "type": "toplist",
                            "requests": [
                                {
                                    "queries": [
                                        {
                                            "data_source": "security_signals",
                                            "name": "query1",
                                            "indexes": [
                                                "*"
                                            ],
                                            "compute": {
                                                "aggregation": "count"
                                            },
                                            "group_by": [
                                                {
                                                    "facet": "@workflow.rule.name",
                                                    "limit": 10,
                                                    "sort": {
                                                        "order": "desc",
                                                        "aggregation": "count"
                                                    }
                                                }
                                            ],
                                            "search": {
                                                "query": "source:cisco-identity-intelligence status:critical $Status $Detail-Type $Title $Check-Id $Region"
                                            }
                                        }
                                    ],
                                    "response_format": "scalar",
                                    "conditional_formats": [
                                        {
                                            "comparator": ">",
                                            "value": 0,
                                            "palette": "custom_bg",
                                            "custom_bg_color": "#bc303c"
                                        }
                                    ],
                                    "formulas": [
                                        {
                                            "formula": "query1"
                                        }
                                    ],
                                    "sort": {
                                        "count": 10,
                                        "order_by": [
                                            {
                                                "type": "formula",
                                                "index": 0,
                                                "order": "desc"
                                            }
                                        ]
                                    }
                                }
                            ],
                            "style": {
                                "display": {
                                    "type": "stacked",
                                    "legend": "automatic"
                                }
                            }
                        },
                        "layout": {
                            "x": 4,
                            "y": 1,
                            "width": 8,
                            "height": 4
                        }
                    },
                    {
                        "id": 6036737878980402,
                        "definition": {
                            "title": "HIGHs",
                            "title_size": "16",
                            "title_align": "left",
                            "type": "query_value",
                            "requests": [
                                {
                                    "response_format": "scalar",
                                    "queries": [
                                        {
                                            "data_source": "security_signals",
                                            "name": "query1",
                                            "indexes": [
                                                "*"
                                            ],
                                            "compute": {
                                                "aggregation": "count"
                                            },
                                            "group_by": [],
                                            "search": {
                                                "query": "status:high source:cisco-identity-intelligence $Status $Detail-Type $Title $Check-Id $Region"
                                            }
                                        }
                                    ],
                                    "formulas": [
                                        {
                                            "formula": "query1"
                                        }
                                    ],
                                    "conditional_formats": [
                                        {
                                            "comparator": ">",
                                            "value": 0,
                                            "palette": "custom_bg",
                                            "custom_bg_color": "#d33043"
                                        }
                                    ]
                                }
                            ],
                            "autoscale": true,
                            "precision": 2
                        },
                        "layout": {
                            "x": 0,
                            "y": 3,
                            "width": 2,
                            "height": 2
                        }
                    },
                    {
                        "id": 3941590353452270,
                        "definition": {
                            "title": "INFOs",
                            "title_size": "16",
                            "title_align": "left",
                            "type": "query_value",
                            "requests": [
                                {
                                    "response_format": "scalar",
                                    "queries": [
                                        {
                                            "data_source": "security_signals",
                                            "name": "query1",
                                            "indexes": [
                                                "*"
                                            ],
                                            "compute": {
                                                "aggregation": "count"
                                            },
                                            "group_by": [],
                                            "search": {
                                                "query": "status:info source:cisco-identity-intelligence $Status $Detail-Type $Title $Check-Id $Region"
                                            }
                                        }
                                    ],
                                    "formulas": [
                                        {
                                            "formula": "query1"
                                        }
                                    ],
                                    "conditional_formats": [
                                        {
                                            "comparator": ">",
                                            "value": 0,
                                            "palette": "custom_bg",
                                            "custom_bg_color": "#84c1e0"
                                        }
                                    ]
                                }
                            ],
                            "autoscale": true,
                            "precision": 2
                        },
                        "layout": {
                            "x": 2,
                            "y": 3,
                            "width": 2,
                            "height": 1
                        }
                    },
                    {
                        "id": 5886455123607734,
                        "definition": {
                            "title": "LOWs",
                            "title_size": "16",
                            "title_align": "left",
                            "type": "query_value",
                            "requests": [
                                {
                                    "response_format": "scalar",
                                    "queries": [
                                        {
                                            "data_source": "security_signals",
                                            "name": "query1",
                                            "indexes": [
                                                "*"
                                            ],
                                            "compute": {
                                                "aggregation": "count"
                                            },
                                            "group_by": [],
                                            "search": {
                                                "query": "status:low source:cisco-identity-intelligence $Status $Detail-Type $Title $Check-Id $Region"
                                            }
                                        }
                                    ],
                                    "formulas": [
                                        {
                                            "formula": "query1"
                                        }
                                    ],
                                    "conditional_formats": [
                                        {
                                            "comparator": ">",
                                            "value": 0,
                                            "palette": "custom_bg",
                                            "custom_bg_color": "#ffb52b"
                                        }
                                    ]
                                }
                            ],
                            "autoscale": true,
                            "precision": 2
                        },
                        "layout": {
                            "x": 2,
                            "y": 4,
                            "width": 2,
                            "height": 1
                        }
                    },
                    {
                        "id": 4007590893086330,
                        "definition": {
                            "title": "High Security Signals",
                            "title_size": "16",
                            "title_align": "left",
                            "type": "toplist",
                            "requests": [
                                {
                                    "queries": [
                                        {
                                            "data_source": "security_signals",
                                            "name": "query1",
                                            "indexes": [
                                                "*"
                                            ],
                                            "compute": {
                                                "aggregation": "count"
                                            },
                                            "group_by": [
                                                {
                                                    "facet": "@workflow.rule.name",
                                                    "limit": 10,
                                                    "sort": {
                                                        "order": "desc",
                                                        "aggregation": "count"
                                                    }
                                                }
                                            ],
                                            "search": {
                                                "query": "source:cisco-identity-intelligence status:high $Status $Detail-Type $Title $Check-Id $Region"
                                            }
                                        }
                                    ],
                                    "response_format": "scalar",
                                    "conditional_formats": [
                                        {
                                            "comparator": ">",
                                            "value": 0,
                                            "palette": "custom_bg",
                                            "custom_bg_color": "#d33043"
                                        }
                                    ],
                                    "formulas": [
                                        {
                                            "formula": "query1"
                                        }
                                    ],
                                    "sort": {
                                        "count": 10,
                                        "order_by": [
                                            {
                                                "type": "formula",
                                                "index": 0,
                                                "order": "desc"
                                            }
                                        ]
                                    }
                                }
                            ],
                            "style": {
                                "display": {
                                    "type": "stacked",
                                    "legend": "automatic"
                                }
                            }
                        },
                        "layout": {
                            "x": 0,
                            "y": 5,
                            "width": 6,
                            "height": 4
                        }
                    },
                    {
                        "id": 5030896927969244,
                        "definition": {
                            "title": "Medium Security Signals",
                            "title_size": "16",
                            "title_align": "left",
                            "type": "toplist",
                            "requests": [
                                {
                                    "queries": [
                                        {
                                            "data_source": "security_signals",
                                            "name": "query1",
                                            "indexes": [
                                                "*"
                                            ],
                                            "compute": {
                                                "aggregation": "count"
                                            },
                                            "group_by": [
                                                {
                                                    "facet": "@workflow.rule.name",
                                                    "limit": 10,
                                                    "sort": {
                                                        "order": "desc",
                                                        "aggregation": "count"
                                                    }
                                                }
                                            ],
                                            "search": {
                                                "query": "source:cisco-identity-intelligence status:medium $Status $Detail-Type $Title $Check-Id $Region"
                                            }
                                        }
                                    ],
                                    "response_format": "scalar",
                                    "conditional_formats": [
                                        {
                                            "comparator": ">",
                                            "value": 0,
                                            "palette": "custom_bg",
                                            "custom_bg_color": "#e5a21c"
                                        }
                                    ],
                                    "formulas": [
                                        {
                                            "formula": "query1"
                                        }
                                    ],
                                    "sort": {
                                        "count": 10,
                                        "order_by": [
                                            {
                                                "type": "formula",
                                                "index": 0,
                                                "order": "desc"
                                            }
                                        ]
                                    }
                                }
                            ],
                            "style": {
                                "display": {
                                    "type": "stacked",
                                    "legend": "automatic"
                                }
                            }
                        },
                        "layout": {
                            "x": 6,
                            "y": 5,
                            "width": 6,
                            "height": 4
                        }
                    }
                ]
            },
            "layout": {
                "x": 0,
                "y": 8,
                "width": 12,
                "height": 10
            }
        },
        {
            "id": 5551393917501738,
            "definition": {
                "title": "Failed Check Details",
                "background_color": "vivid_blue",
                "show_title": true,
                "type": "group",
                "layout_type": "ordered",
                "widgets": [
                    {
                        "id": 1051140394439642,
                        "definition": {
                            "title": "Total Critical Checks",
                            "title_size": "16",
                            "title_align": "left",
                            "type": "query_value",
                            "requests": [
                                {
                                    "response_format": "scalar",
                                    "queries": [
                                        {
                                            "data_source": "logs",
                                            "name": "query1",
                                            "indexes": [
                                                "*"
                                            ],
                                            "compute": {
                                                "aggregation": "count"
                                            },
                                            "group_by": [],
                                            "search": {
                                                "query": "source:cisco-identity-intelligence @detail.severity:critical $Status $Detail-Type $Title $Check-Id $Region"
                                            },
                                            "storage": "hot"
                                        }
                                    ],
                                    "formulas": [
                                        {
                                            "formula": "query1"
                                        }
                                    ],
                                    "conditional_formats": [
                                        {
                                            "comparator": ">",
                                            "value": 0,
                                            "palette": "black_on_light_red"
                                        }
                                    ]
                                }
                            ],
                            "autoscale": true,
                            "precision": 2
                        },
                        "layout": {
                            "x": 0,
                            "y": 0,
                            "width": 3,
                            "height": 4
                        }
                    },
                    {
                        "id": 2177060554158224,
                        "definition": {
                            "title": "Total High Checks",
                            "title_size": "16",
                            "title_align": "left",
                            "type": "query_value",
                            "requests": [
                                {
                                    "response_format": "scalar",
                                    "queries": [
                                        {
                                            "data_source": "logs",
                                            "name": "query1",
                                            "indexes": [
                                                "*"
                                            ],
                                            "compute": {
                                                "aggregation": "count"
                                            },
                                            "group_by": [],
                                            "search": {
                                                "query": "source:cisco-identity-intelligence @detail.severity:high $Status $Detail-Type $Title $Check-Id $Region"
                                            },
                                            "storage": "hot"
                                        }
                                    ],
                                    "formulas": [
                                        {
                                            "formula": "query1"
                                        }
                                    ],
                                    "conditional_formats": [
                                        {
                                            "comparator": ">",
                                            "value": 0,
                                            "palette": "black_on_light_red"
                                        }
                                    ]
                                }
                            ],
                            "autoscale": true,
                            "precision": 2
                        },
                        "layout": {
                            "x": 3,
                            "y": 0,
                            "width": 3,
                            "height": 4
                        }
                    },
                    {
                        "id": 1922593512656714,
                        "definition": {
                            "title": "Total Medium Checks",
                            "title_size": "16",
                            "title_align": "left",
                            "type": "query_value",
                            "requests": [
                                {
                                    "response_format": "scalar",
                                    "queries": [
                                        {
                                            "data_source": "logs",
                                            "name": "query1",
                                            "indexes": [
                                                "*"
                                            ],
                                            "compute": {
                                                "aggregation": "count"
                                            },
                                            "group_by": [],
                                            "search": {
                                                "query": "source:cisco-identity-intelligence @detail.severity:medium $Status $Detail-Type $Title $Check-Id $Region"
                                            },
                                            "storage": "hot"
                                        }
                                    ],
                                    "formulas": [
                                        {
                                            "formula": "query1"
                                        }
                                    ],
                                    "conditional_formats": [
                                        {
                                            "comparator": ">",
                                            "value": 0,
                                            "palette": "black_on_light_yellow"
                                        }
                                    ]
                                }
                            ],
                            "autoscale": true,
                            "precision": 2
                        },
                        "layout": {
                            "x": 6,
                            "y": 0,
                            "width": 3,
                            "height": 4
                        }
                    },
                    {
                        "id": 4531226313734728,
                        "definition": {
                            "title": "Total Moderate Checks",
                            "title_size": "16",
                            "title_align": "left",
                            "type": "query_value",
                            "requests": [
                                {
                                    "response_format": "scalar",
                                    "queries": [
                                        {
                                            "data_source": "logs",
                                            "name": "query1",
                                            "indexes": [
                                                "*"
                                            ],
                                            "compute": {
                                                "aggregation": "count"
                                            },
                                            "group_by": [],
                                            "search": {
                                                "query": "source:cisco-identity-intelligence @detail.severity:moderate $Status $Detail-Type $Title $Check-Id $Region"
                                            },
                                            "storage": "hot"
                                        }
                                    ],
                                    "formulas": [
                                        {
                                            "formula": "query1"
                                        }
                                    ],
                                    "conditional_formats": [
                                        {
                                            "comparator": ">",
                                            "value": 0,
                                            "palette": "black_on_light_yellow"
                                        }
                                    ]
                                }
                            ],
                            "autoscale": true,
                            "precision": 2
                        },
                        "layout": {
                            "x": 9,
                            "y": 0,
                            "width": 3,
                            "height": 4
                        }
                    },
                    {
                        "id": 7621062407708146,
                        "definition": {
                            "title": "Total Low Checks",
                            "title_size": "16",
                            "title_align": "left",
                            "type": "query_value",
                            "requests": [
                                {
                                    "response_format": "scalar",
                                    "queries": [
                                        {
                                            "data_source": "logs",
                                            "name": "query1",
                                            "indexes": [
                                                "*"
                                            ],
                                            "compute": {
                                                "aggregation": "count"
                                            },
                                            "group_by": [],
                                            "search": {
                                                "query": "source:cisco-identity-intelligence @detail.severity:low $Status $Detail-Type $Title $Check-Id $Region"
                                            },
                                            "storage": "hot"
                                        }
                                    ],
                                    "formulas": [
                                        {
                                            "formula": "query1"
                                        }
                                    ],
                                    "conditional_formats": [
                                        {
                                            "comparator": ">",
                                            "value": 0,
                                            "palette": "black_on_light_yellow"
                                        }
                                    ]
                                }
                            ],
                            "autoscale": true,
                            "precision": 2
                        },
                        "layout": {
                            "x": 0,
                            "y": 4,
                            "width": 3,
                            "height": 4
                        }
                    },
                    {
                        "id": 6241857123186234,
                        "definition": {
                            "title": "Distribution by Detail Type",
                            "title_size": "16",
                            "title_align": "left",
                            "requests": [
                                {
                                    "response_format": "scalar",
                                    "formulas": [
                                        {
                                            "formula": "query1"
                                        }
                                    ],
                                    "queries": [
                                        {
                                            "data_source": "logs",
                                            "name": "query1",
                                            "indexes": [
                                                "*"
                                            ],
                                            "compute": {
                                                "aggregation": "count"
                                            },
                                            "group_by": [
                                                {
                                                    "facet": "@detail-type",
                                                    "limit": 10,
                                                    "sort": {
                                                        "order": "desc",
                                                        "aggregation": "count"
                                                    }
                                                }
                                            ],
                                            "search": {
                                                "query": "source:cisco-identity-intelligence $Status $Detail-Type $Title $Check-Id $Region"
                                            },
                                            "storage": "hot"
                                        }
                                    ],
                                    "style": {
                                        "palette": "datadog16"
                                    },
                                    "sort": {
                                        "count": 10,
                                        "order_by": [
                                            {
                                                "type": "formula",
                                                "index": 0,
                                                "order": "desc"
                                            }
                                        ]
                                    }
                                }
                            ],
                            "type": "sunburst",
                            "legend": {
                                "type": "table"
                            }
                        },
                        "layout": {
                            "x": 3,
                            "y": 4,
                            "width": 9,
                            "height": 4
                        }
                    },
                    {
                        "id": 6347099837281738,
                        "definition": {
                            "title": "Top 10 Users With Failed Checks",
                            "title_size": "16",
                            "title_align": "left",
                            "type": "toplist",
                            "requests": [
                                {
                                    "queries": [
                                        {
                                            "data_source": "logs",
                                            "name": "query1",
                                            "indexes": [
                                                "*"
                                            ],
                                            "compute": {
                                                "aggregation": "count"
                                            },
                                            "group_by": [
                                                {
                                                    "facet": "@detail.usersFailing",
                                                    "limit": 10,
                                                    "sort": {
                                                        "order": "desc",
                                                        "aggregation": "count"
                                                    }
                                                }
                                            ],
                                            "search": {
                                                "query": "source:cisco-identity-intelligence $Status $Detail-Type $Title $Check-Id $Region"
                                            },
                                            "storage": "hot"
                                        }
                                    ],
                                    "response_format": "scalar",
                                    "formulas": [
                                        {
                                            "formula": "query1"
                                        }
                                    ],
                                    "sort": {
                                        "count": 10,
                                        "order_by": [
                                            {
                                                "type": "formula",
                                                "index": 0,
                                                "order": "desc"
                                            }
                                        ]
                                    }
                                }
                            ],
                            "style": {
                                "display": {
                                    "type": "stacked",
                                    "legend": "automatic"
                                },
                                "scaling": "relative"
                            }
                        },
                        "layout": {
                            "x": 0,
                            "y": 8,
                            "width": 3,
                            "height": 4
                        }
                    },
                    {
                        "id": 935209002998876,
                        "definition": {
                            "title": "Distribution by Check ID",
                            "title_size": "16",
                            "title_align": "left",
                            "requests": [
                                {
                                    "response_format": "scalar",
                                    "formulas": [
                                        {
                                            "formula": "query1"
                                        }
                                    ],
                                    "queries": [
                                        {
                                            "data_source": "logs",
                                            "name": "query1",
                                            "indexes": [
                                                "*"
                                            ],
                                            "compute": {
                                                "aggregation": "count"
                                            },
                                            "group_by": [
                                                {
                                                    "facet": "@detail.checkId",
                                                    "limit": 10,
                                                    "sort": {
                                                        "order": "desc",
                                                        "aggregation": "count"
                                                    }
                                                }
                                            ],
                                            "search": {
                                                "query": "source:cisco-identity-intelligence $Status $Detail-Type $Title $Check-Id $Region"
                                            },
                                            "storage": "hot"
                                        }
                                    ],
                                    "style": {
                                        "palette": "datadog16"
                                    },
                                    "sort": {
                                        "count": 10,
                                        "order_by": [
                                            {
                                                "type": "formula",
                                                "index": 0,
                                                "order": "desc"
                                            }
                                        ]
                                    }
                                }
                            ],
                            "type": "sunburst",
                            "legend": {
                                "type": "table"
                            }
                        },
                        "layout": {
                            "x": 3,
                            "y": 8,
                            "width": 9,
                            "height": 4
                        }
                    },
                    {
                        "id": 8466250297852710,
                        "definition": {
                            "title": "Distribution by Check Id and Description",
                            "title_size": "16",
                            "title_align": "left",
                            "type": "query_table",
                            "requests": [
                                {
                                    "queries": [
                                        {
                                            "data_source": "logs",
                                            "name": "query1",
                                            "indexes": [
                                                "*"
                                            ],
                                            "compute": {
                                                "aggregation": "cardinality",
                                                "metric": "@detail.id"
                                            },
                                            "group_by": [
                                                {
                                                    "facet": "@detail.checkId",
                                                    "limit": 10,
                                                    "sort": {
                                                        "order": "desc",
                                                        "aggregation": "cardinality",
                                                        "metric": "@detail.id"
                                                    }
                                                },
                                                {
                                                    "facet": "@detail.description",
                                                    "limit": 10,
                                                    "sort": {
                                                        "order": "desc",
                                                        "aggregation": "cardinality",
                                                        "metric": "@detail.id"
                                                    }
                                                }
                                            ],
                                            "search": {
                                                "query": "source:cisco-identity-intelligence $Status $Detail-Type $Title $Check-Id $Region"
                                            },
                                            "storage": "hot"
                                        }
                                    ],
                                    "response_format": "scalar",
                                    "text_formats": [
                                        [],
                                        [
                                            {
                                                "match": {
                                                    "type": "is",
                                                    "value": ""
                                                },
                                                "palette": "white_on_green"
                                            }
                                        ]
                                    ],
                                    "sort": {
                                        "count": 100,
                                        "order_by": [
                                            {
                                                "type": "formula",
                                                "index": 0,
                                                "order": "desc"
                                            }
                                        ]
                                    },
                                    "formulas": [
                                        {
                                            "cell_display_mode": "bar",
                                            "alias": "count",
                                            "formula": "query1"
                                        }
                                    ]
                                }
                            ],
                            "has_search_bar": "auto"
                        },
                        "layout": {
                            "x": 0,
                            "y": 12,
                            "width": 12,
                            "height": 4
                        }
                    },
                    {
                        "id": 8016099397285314,
                        "definition": {
                            "title": "Distribution by Check Id and Recommended Actions",
                            "title_size": "16",
                            "title_align": "left",
                            "type": "query_table",
                            "requests": [
                                {
                                    "queries": [
                                        {
                                            "data_source": "logs",
                                            "name": "query1",
                                            "indexes": [
                                                "*"
                                            ],
                                            "compute": {
                                                "aggregation": "cardinality",
                                                "metric": "@detail.id"
                                            },
                                            "group_by": [
                                                {
                                                    "facet": "@detail.checkId",
                                                    "limit": 10,
                                                    "sort": {
                                                        "order": "desc",
                                                        "aggregation": "cardinality",
                                                        "metric": "@detail.id"
                                                    }
                                                },
                                                {
                                                    "facet": "@detail.recommendedActions",
                                                    "limit": 10,
                                                    "sort": {
                                                        "order": "desc",
                                                        "aggregation": "cardinality",
                                                        "metric": "@detail.id"
                                                    }
                                                }
                                            ],
                                            "search": {
                                                "query": "source:cisco-identity-intelligence $Status $Detail-Type $Title $Check-Id $Region"
                                            },
                                            "storage": "hot"
                                        }
                                    ],
                                    "response_format": "scalar",
                                    "sort": {
                                        "count": 100,
                                        "order_by": [
                                            {
                                                "type": "formula",
                                                "index": 0,
                                                "order": "desc"
                                            }
                                        ]
                                    },
                                    "formulas": [
                                        {
                                            "cell_display_mode": "bar",
                                            "alias": "count",
                                            "formula": "query1"
                                        }
                                    ]
                                }
                            ],
                            "has_search_bar": "auto"
                        },
                        "layout": {
                            "x": 0,
                            "y": 16,
                            "width": 12,
                            "height": 4
                        }
                    },
                    {
                        "id": 3835871135175978,
                        "definition": {
                            "title": "Threat Intel Details",
                            "title_size": "16",
                            "title_align": "left",
                            "type": "query_table",
                            "requests": [
                                {
                                    "queries": [
                                        {
                                            "data_source": "logs",
                                            "name": "query1",
                                            "indexes": [
                                                "*"
                                            ],
                                            "compute": {
                                                "aggregation": "count"
                                            },
                                            "group_by": [
                                                {
                                                    "facet": "@detail.checkId",
                                                    "limit": 2,
                                                    "sort": {
                                                        "order": "desc",
                                                        "aggregation": "count"
                                                    }
                                                },
                                                {
                                                    "facet": "@threat_intel.results.category",
                                                    "limit": 2,
                                                    "sort": {
                                                        "order": "desc",
                                                        "aggregation": "count"
                                                    }
                                                },
                                                {
                                                    "facet": "@threat_intel.results.intention",
                                                    "limit": 2,
                                                    "sort": {
                                                        "order": "desc",
                                                        "aggregation": "count"
                                                    }
                                                },
                                                {
                                                    "facet": "@threat_intel.results.additional_data.client.behaviors",
                                                    "limit": 2,
                                                    "sort": {
                                                        "order": "desc",
                                                        "aggregation": "count"
                                                    }
                                                },
                                                {
                                                    "facet": "@threat_intel.results.source.url",
                                                    "limit": 2,
                                                    "sort": {
                                                        "order": "desc",
                                                        "aggregation": "count"
                                                    }
                                                },
                                                {
                                                    "facet": "@threat_intel.results.type",
                                                    "limit": 2,
                                                    "sort": {
                                                        "order": "desc",
                                                        "aggregation": "count"
                                                    }
                                                }
                                            ],
                                            "search": {
                                                "query": "$Status $Detail-Type $Title $Check-Id $Region"
                                            },
                                            "storage": "hot"
                                        }
                                    ],
                                    "response_format": "scalar",
                                    "sort": {
                                        "count": 64,
                                        "order_by": [
                                            {
                                                "type": "formula",
                                                "index": 0,
                                                "order": "desc"
                                            }
                                        ]
                                    },
                                    "formulas": [
                                        {
                                            "cell_display_mode": "bar",
                                            "alias": "Count",
                                            "formula": "query1"
                                        }
                                    ]
                                }
                            ],
                            "has_search_bar": "auto"
                        },
                        "layout": {
                            "x": 0,
                            "y": 20,
                            "width": 12,
                            "height": 4
                        }
                    },
                    {
                        "id": 5671063317847920,
                        "definition": {
                            "title": "Distribution by Region",
                            "title_size": "16",
                            "title_align": "left",
                            "type": "query_table",
                            "requests": [
                                {
                                    "queries": [
                                        {
                                            "data_source": "logs",
                                            "name": "query1",
                                            "indexes": [
                                                "*"
                                            ],
                                            "compute": {
                                                "aggregation": "cardinality",
                                                "metric": "@id"
                                            },
                                            "group_by": [
                                                {
                                                    "facet": "@region",
                                                    "limit": 10,
                                                    "sort": {
                                                        "order": "desc",
                                                        "aggregation": "cardinality",
                                                        "metric": "@id"
                                                    }
                                                }
                                            ],
                                            "search": {
                                                "query": "source:cisco-identity-intelligence $Status $Detail-Type $Title $Check-Id $Region"
                                            },
                                            "storage": "hot"
                                        }
                                    ],
                                    "response_format": "scalar",
                                    "sort": {
                                        "count": 10,
                                        "order_by": [
                                            {
                                                "type": "formula",
                                                "index": 0,
                                                "order": "desc"
                                            }
                                        ]
                                    },
                                    "formulas": [
                                        {
                                            "cell_display_mode": "number",
                                            "alias": "Count",
                                            "formula": "query1"
                                        }
                                    ]
                                }
                            ],
                            "has_search_bar": "auto"
                        },
                        "layout": {
                            "x": 0,
                            "y": 24,
                            "width": 4,
                            "height": 4
                        }
                    },
                    {
                        "id": 8349736624356392,
                        "definition": {
                            "title": "Distribution by Version",
                            "title_size": "16",
                            "title_align": "left",
                            "requests": [
                                {
                                    "response_format": "scalar",
                                    "formulas": [
                                        {
                                            "formula": "query1"
                                        }
                                    ],
                                    "queries": [
                                        {
                                            "data_source": "logs",
                                            "name": "query1",
                                            "indexes": [
                                                "*"
                                            ],
                                            "compute": {
                                                "aggregation": "count"
                                            },
                                            "group_by": [
                                                {
                                                    "facet": "@version",
                                                    "limit": 10,
                                                    "sort": {
                                                        "order": "desc",
                                                        "aggregation": "count"
                                                    }
                                                }
                                            ],
                                            "search": {
                                                "query": "source:cisco-identity-intelligence $Status $Detail-Type $Title $Check-Id $Region"
                                            },
                                            "storage": "hot"
                                        }
                                    ],
                                    "style": {
                                        "palette": "datadog16"
                                    },
                                    "sort": {
                                        "count": 10,
                                        "order_by": [
                                            {
                                                "type": "formula",
                                                "index": 0,
                                                "order": "desc"
                                            }
                                        ]
                                    }
                                }
                            ],
                            "type": "sunburst",
                            "legend": {
                                "type": "table"
                            }
                        },
                        "layout": {
                            "x": 4,
                            "y": 24,
                            "width": 8,
                            "height": 4
                        }
                    },
                    {
                        "id": 3223791196963750,
                        "definition": {
                            "title": "Log Details",
                            "title_size": "16",
                            "title_align": "left",
                            "requests": [
                                {
                                    "response_format": "event_list",
                                    "query": {
                                        "data_source": "logs_stream",
                                        "query_string": "source:cisco-identity-intelligence $Status $Detail-Type $Title $Check-Id $Region ",
                                        "indexes": [],
                                        "storage": "hot",
                                        "sort": {
                                            "order": "desc",
                                            "column": "timestamp"
                                        }
                                    },
                                    "columns": [
                                        {
                                            "field": "status_line",
                                            "width": "auto"
                                        },
                                        {
                                            "field": "timestamp",
                                            "width": "auto"
                                        },
                                        {
                                            "field": "detail.severity",
                                            "width": "auto"
                                        },
                                        {
                                            "field": "detail-type",
                                            "width": "auto"
                                        },
                                        {
                                            "field": "content",
                                            "width": "auto"
                                        },
                                        {
                                            "field": "detail.checkId",
                                            "width": "auto"
                                        },
                                        {
                                            "field": "detail.usersFailing",
                                            "width": "auto"
                                        },
                                        {
                                            "field": "detail.id",
                                            "width": "auto"
                                        },
                                        {
                                            "field": "detail.description",
                                            "width": "auto"
                                        },
                                        {
                                            "field": "detail.recommendedActions",
                                            "width": "auto"
                                        },
                                        {
                                            "field": "source",
                                            "width": "auto"
                                        },
                                        {
                                            "field": "region",
                                            "width": "auto"
                                        },
                                        {
                                            "field": "version",
                                            "width": "auto"
                                        }
                                    ]
                                }
                            ],
                            "type": "list_stream"
                        },
                        "layout": {
                            "x": 0,
                            "y": 28,
                            "width": 12,
                            "height": 4
                        }
                    }
                ]
            },
            "layout": {
                "x": 0,
                "y": 18,
                "width": 12,
                "height": 33
            }
        }
    ],
    "template_variables": [
        {
            "name": "Status",
            "prefix": "@status",
            "available_values": [],
            "default": "*"
        },
        {
            "name": "Detail-Type",
            "prefix": "@detail-type",
            "available_values": [],
            "default": "*"
        },
        {
            "name": "Title",
            "prefix": "@detail.title",
            "available_values": [],
            "default": "*"
        },
        {
            "name": "Check-Id",
            "prefix": "@detail.checkId",
            "available_values": [],
            "default": "*"
        },
        {
            "name": "Region",
            "prefix": "@region",
            "available_values": [],
            "default": "*"
        }
    ],
    "layout_type": "ordered",
    "notify_list": [],
    "reflow_type": "fixed"
}